LICENSE
README.md
setup.py
tap_sftp/__init__.py
tap_sftp/client.py
tap_sftp/discover.py
tap_sftp/helper.py
tap_sftp/stats.py
tap_sftp/sync.py
tap_sftp.egg-info/PKG-INFO
tap_sftp.egg-info/SOURCES.txt
tap_sftp.egg-info/dependency_links.txt
tap_sftp.egg-info/entry_points.txt
tap_sftp.egg-info/requires.txt
tap_sftp.egg-info/top_level.txt
tests/test_sftp_delimiter.py
tests/test_sftp_discovery.py
tests/test_sftp_empty_csv_in_gz.py
tests/test_sftp_empty_csv_in_zip.py
tests/test_sftp_encoding.py
tests/test_sftp_gzip.py
tests/test_sftp_sorted_files.py
tests/test_sftp_start_date_multiple_stream.py
tests/test_sftp_start_date_one_stream.py
tests/test_sftp_sync.py
tests/test_sftp_zip.py