Metadata-Version: 2.1
Name: tap-sftp
Version: 1.3.0
Summary: Singer.io tap for extracting data
Home-page: http://singer.io
Author: Stitch
Classifier: Programming Language :: Python :: 3 :: Only
License-File: LICENSE
Requires-Dist: singer-python==5.13.2
Requires-Dist: paramiko==3.5.1
Requires-Dist: backoff==1.10.0
Requires-Dist: singer-encodings==0.1.4
Provides-Extra: dev
Requires-Dist: ipdb; extra == "dev"
Requires-Dist: pylint; extra == "dev"
Requires-Dist: nose; extra == "dev"
Provides-Extra: test
Requires-Dist: paramiko==3.5.1; extra == "test"
